bilibili_sdk/__init__.py
bilibili_sdk/client/__init__.py
bilibili_sdk/client/api.py
bilibili_sdk/client/base.py
bilibili_sdk/client/download.py
bilibili_sdk/client/member.py
bilibili_sdk/common/__init__.py
bilibili_sdk/common/sign.py
bilibili_sdk/common/utils.py
bilibili_sdk/config/__init__.py
bilibili_sdk/config/settings.py
bilibili_sdk/dto/__init__.py
bilibili_sdk/dto/acc_info.py
bilibili_sdk/dto/archive.py
bilibili_sdk/dto/base.py
bilibili_sdk/dto/nav.py
bilibili_sdk/dto/online.py
bilibili_sdk/dto/video_stream.py
bilibili_sdk/enums/__init__.py
bilibili_sdk/enums/archive.py
bilibili_sdk-0.1.3.dist-info/METADATA
bilibili_sdk-0.1.3.dist-info/WHEEL
bilibili_sdk-0.1.3.dist-info/licenses/LICENSE
bilibili_sdk-0.1.3.dist-info/RECORD
