Metadata-Version: 2.4
Name: bilibili-sdk
Version: 0.1.3
Author-email: wxnacy <wxnacy@gmail.com>
License-Expression: MIT
License-File: LICENSE
Requires-Python: >=3.11
Requires-Dist: pydantic-settings>=2.6.1
Requires-Dist: wpy>=0.7.6
Provides-Extra: dev
Requires-Dist: pytest-asyncio>=0.24.0; extra == 'dev'
Requires-Dist: pytest>=8.3.3; extra == 'dev'
Requires-Dist: rich>=13.9.4; extra == 'dev'
